modulass/__init__.py
modulass/__main__.py
modulass-0.0.1.dist-info/METADATA
modulass-0.0.1.dist-info/WHEEL
modulass-0.0.1.dist-info/entry_points.txt
modulass-0.0.1.dist-info/licenses/LICENSE
modulass-0.0.1.dist-info/RECORD
