Metadata-Version: 2.1
Name: modulass
Version: 0.0.1
Summary: Transform a module into a class
Project-URL: Homepage, https://github.com/fumitoh/modulass
Author-email: Fumito Hamamura <fumito.ham@gmail.com>
License: MIT License
License-File: LICENSE
Classifier: License :: OSI Approved :: MIT License
Classifier: Operating System :: OS Independent
Classifier: Programming Language :: Python :: 3
Requires-Python: >=3.8
Requires-Dist: libcst
